ipymini/__init__.py
ipymini/__main__.py
ipymini/bridge.py
ipymini/comms.py
ipymini/kernel.py
ipymini/debug/README.md
ipymini/debug/__init__.py
ipymini/debug/cells.py
ipymini/debug/dap.py
ipymini/debug/flags.py
ipymini/debug/infra.py
ipymini/shell/README.md
ipymini/shell/__init__.py
ipymini/shell/comms.py
ipymini/shell/shell.py
ipymini/term/README.md
ipymini/term/__init__.py
ipymini/term/display.py
ipymini/term/io.py
ipymini/term/ipython_capture.py
ipymini/term/streams.py
ipymini/zmqthread/README.md
ipymini/zmqthread/__init__.py
ipymini/zmqthread/async_router.py
ipymini/zmqthread/heartbeat.py
ipymini/zmqthread/iopub.py
ipymini/zmqthread/queues.py
ipymini/zmqthread/stdin.py
ipymini-0.1.5.dist-info/METADATA
ipymini-0.1.5.dist-info/WHEEL
ipymini-0.1.5.dist-info/entry_points.txt
ipymini-0.1.5.dist-info/licenses/LICENSE
ipymini-0.1.5.dist-info/RECORD
