Metadata-Version: 2.4
Name: ipymini
Version: 0.1.5
Summary: A small, readable, Python-only Jupyter kernel with strong IPython parity.
License-File: LICENSE
Requires-Python: >=3.11
Requires-Dist: comm>=0.2.3
Requires-Dist: fastcore>=1.5
Requires-Dist: ipython>=8.18
Requires-Dist: jupyter-client>=8.6
Requires-Dist: jupyter-core>=5.5
Requires-Dist: pyzmq>=25.1
Provides-Extra: dev
Requires-Dist: debugpy>=1.8; extra == 'dev'
Requires-Dist: hatch; extra == 'dev'
Requires-Dist: ipykernel>=6.29; extra == 'dev'
Requires-Dist: matplotlib>=3.8; extra == 'dev'
Requires-Dist: murmurhash2; extra == 'dev'
Requires-Dist: pytest>=7.4; extra == 'dev'
Requires-Dist: twine; extra == 'dev'
Provides-Extra: test
Requires-Dist: debugpy>=1.8; extra == 'test'
Requires-Dist: ipykernel>=6.29; extra == 'test'
Requires-Dist: matplotlib>=3.8; extra == 'test'
Requires-Dist: murmurhash2; extra == 'test'
Requires-Dist: pytest>=7.4; extra == 'test'
